ocspbuilder/__init__.py
ocspbuilder-0.10.1.dist-info/DESCRIPTION.rst
ocspbuilder-0.10.1.dist-info/METADATA
ocspbuilder-0.10.1.dist-info/RECORD
ocspbuilder-0.10.1.dist-info/WHEEL
ocspbuilder-0.10.1.dist-info/metadata.json
ocspbuilder-0.10.1.dist-info/top_level.txt
